Workbook
Name aporte_mensal: Principal!$D$11
Name patrimonio: Principal!$D$14
Name porcentagem: Principal!$D$6
Name qtd_anos: Principal!$D$12
Name rendimento_carteira: Principal!$D$5
Name salario: Principal!$D$4
Name taxa_investimento: Principal!$D$13

Sheet Principal
B3: Dados iniciais
B4: Salário | D4: 5000
B5: Rendimento da Carteira | D5: 0.008
B6: Porcentagem do salário para investir | D6: 0.2
B7: Valor do Investimento | D7: =salario*porcentagem -> 1000
B10: Investimento
B11: Aporte Mensal | D11: =D7 -> 1000
B12: Quantidade de Anos | D12: 3
B13: Taxa de Rendimento Mensal | D13: 0.0107
B14: Patrimônio Acumulado | D14: =FV(taxa_investimento,qtd_anos*12,aporte_mensal*-1) -> 43635.848
B15: Dividendo Mensal | D15: =patrimonio*rendimento_carteira -> 349.08678
B18: Horizontes | D18: Dividendo
A19: 2 | B19: Em 2 anos | C19: =FV(taxa_investimento,A19*12,aporte_mensal*-1) -> 27198.522 | D19: =C19*rendimento_carteira -> 217.58817
A20: 5 | B20: Em 5 anos | C20: =FV(taxa_investimento,A20*12,aporte_mensal*-1) -> 83533.456 | D20: =C20*rendimento_carteira -> 668.26765
A21: 10 | B21: Em 10 anos | C21: =FV(taxa_investimento,A21*12,aporte_mensal*-1) -> 241729.78 | D21: =C21*rendimento_carteira -> 1933.8383
A22: 30 | B22: Em 30 anos | C22: =FV(taxa_investimento,A22*12,aporte_mensal*-1) -> 4218076.6 | D22: =C22*rendimento_carteira -> 33744.613
A23: 50 | B23: Em 50 anos | C23: =FV(taxa_investimento,A23*12,aporte_mensal*-1) -> 55366003 | D23: =C23*rendimento_carteira -> 442928.02
B26: PERFIL | C26: Moderado
B27: VALOR A SER INVESTIDO POR MÊS | C27: =aporte_mensal -> 1000
B29: TIPO DE FII | C29: Percentual Sugerido | D29: Valores
B30: PAPEL | C30: =VLOOKUP($C$26&"-"&B30,lista!B:E,4,FALSE) -> 0.4 | D30: =$C$27*C30 -> 400
B31: TIJOLO | C31: =VLOOKUP($C$26&"-"&B31,lista!B:E,4,FALSE) -> 0.35 | D31: =$C$27*C31 -> 350
B32: HÍBRIDOS | C32: =VLOOKUP($C$26&"-"&B32,lista!B:E,4,FALSE) -> 0.1 | D32: =$C$27*C32 -> 100
B33: FOFs | C33: =VLOOKUP($C$26&"-"&B33,lista!B:E,4,FALSE) -> 0.05 | D33: =$C$27*C33 -> 50
B34: DESENVOLVIMENTO | C34: =VLOOKUP($C$26&"-"&B34,lista!B:E,4,FALSE) -> 0.05 | D34: =$C$27*C34 -> 50
B35: HOTELARIAS | C35: =VLOOKUP($C$26&"-"&B35,lista!B:E,4,FALSE) -> 0.05 | D35: =$C$27*C35 -> 50
D36: =SUM(D30:D35) -> 1000

Sheet lista
B2: CHAVE | C2: PERFIL | D2: TIPO DE FII | E2: %
B3: Conservador-PAPEL | C3: Conservador | D3: PAPEL | E3: 0.5
B4: Conservador-TIJOLO | C4: Conservador | D4: TIJOLO | E4: 0.3
B5: Conservador-HÍBRIDOS | C5: Conservador | D5: HÍBRIDOS | E5: 0.1
B6: Conservador-FOFs | C6: Conservador | D6: FOFs | E6: 0.1
B7: Conservador-DESENVOLVIMENTO | C7: Conservador | D7: DESENVOLVIMENTO | E7: 0
B8: Conservador-HOTELARIAS | C8: Conservador | D8: HOTELARIAS | E8: 0
B9: Moderado-PAPEL | C9: Moderado | D9: PAPEL | E9: 0.4
B10: Moderado-TIJOLO | C10: Moderado | D10: TIJOLO | E10: 0.35
B11: Moderado-HÍBRIDOS | C11: Moderado | D11: HÍBRIDOS | E11: 0.1
B12: Moderado-FOFs | C12: Moderado | D12: FOFs | E12: 0.05
B13: Moderado-DESENVOLVIMENTO | C13: Moderado | D13: DESENVOLVIMENTO | E13: 0.05
B14: Moderado-HOTELARIAS | C14: Moderado | D14: HOTELARIAS | E14: 0.05
... B20: Agressivo-HOTELARIAS | C20: Agressivo | D20: HOTELARIAS | E20: 0.1
